README.rst
setup.py
crest/__init__.py
crest/cli.py
crest/history.py
crest.egg-info/PKG-INFO
crest.egg-info/SOURCES.txt
crest.egg-info/dependency_links.txt
crest.egg-info/entry_points.txt
crest.egg-info/requires.txt
crest.egg-info/top_level.txt
crest/tests/__init__.py
crest/tests/test_cli.py