Metadata-Version: 1.1
Name: crest
Version: 0.0.1
Summary: CLI to access RESTful service
Home-page: https://github.com/manishtomar/crest
Author: Manish Tomar
Author-email: manish.tomar@gmail.com
License: MIT
Keywords: restful cli
Platform: UNKNOWN
Classifier: Development Status :: 3 - Alpha
Classifier: Environment :: Console
Classifier: Intended Audience :: Developers
Classifier: Intended Audience :: End Users/Desktop
Classifier: License :: OSI Approved :: MIT License
Classifier: Natural Language :: English
Classifier: Programming Language :: Python :: 2 :: Only
Classifier: Programming Language :: Python :: 2.7
Classifier: Topic :: Internet :: WWW/HTTP
